genie/libs/filetransferutils/__init__.py
genie/libs/filetransferutils/exceptions.py
genie/libs/filetransferutils/fileutils.py
genie/libs/filetransferutils/bases/__init__.py
genie/libs/filetransferutils/bases/fileutils.py
genie/libs/filetransferutils/fileserver/__init__.py
genie/libs/filetransferutils/fileserver/plugin.py
genie/libs/filetransferutils/fileserver/server.py
genie/libs/filetransferutils/fileserver/protocols/__init__.py
genie/libs/filetransferutils/fileserver/protocols/ftp.py
genie/libs/filetransferutils/fileserver/protocols/http.py
genie/libs/filetransferutils/fileserver/protocols/scp.py
genie/libs/filetransferutils/fileserver/protocols/tftp.py
genie/libs/filetransferutils/plugins/__init__.py
genie/libs/filetransferutils/plugins/fileutils.py
genie/libs/filetransferutils/plugins/apic/__init__.py
genie/libs/filetransferutils/plugins/apic/fileutils.py
genie/libs/filetransferutils/plugins/ios/__init__.py
genie/libs/filetransferutils/plugins/ios/fileutils.py
genie/libs/filetransferutils/plugins/ios/ftp/__init__.py
genie/libs/filetransferutils/plugins/ios/ftp/fileutils.py
genie/libs/filetransferutils/plugins/ios/http/__init__.py
genie/libs/filetransferutils/plugins/ios/http/fileutils.py
genie/libs/filetransferutils/plugins/ios/scp/__init__.py
genie/libs/filetransferutils/plugins/ios/scp/fileutils.py
genie/libs/filetransferutils/plugins/ios/sftp/__init__.py
genie/libs/filetransferutils/plugins/ios/sftp/fileutils.py
genie/libs/filetransferutils/plugins/ios/tftp/__init__.py
genie/libs/filetransferutils/plugins/ios/tftp/fileutils.py
genie/libs/filetransferutils/plugins/iosxe/__init__.py
genie/libs/filetransferutils/plugins/iosxe/fileutils.py
genie/libs/filetransferutils/plugins/iosxe/ftp/__init__.py
genie/libs/filetransferutils/plugins/iosxe/ftp/fileutils.py
genie/libs/filetransferutils/plugins/iosxe/http/__init__.py
genie/libs/filetransferutils/plugins/iosxe/http/fileutils.py
genie/libs/filetransferutils/plugins/iosxe/scp/__init__.py
genie.libs.filetransferutils-25.9.dist-info/METADATA
genie.libs.filetransferutils-25.9.dist-info/WHEEL
genie.libs.filetransferutils-25.9.dist-info/entry_points.txt
genie.libs.filetransferutils-25.9.dist-info/top_level.txt
genie.libs.filetransferutils-25.9.dist-info/RECORD
